tests/__init__.py
tests/test_definitions.py
tests/test_etymologies.py
tests/test_synonyms.py
tests/test_utils.py
wordpy/__init__.py
wordpy/exceptions.py
wordpy/keys.py
wordpy/utils.py
wordpy/word.py
wordpy-1.1.4.data/scripts/wordpy
wordpy-1.1.4.dist-info/LICENSE
wordpy-1.1.4.dist-info/METADATA
wordpy-1.1.4.dist-info/WHEEL
wordpy-1.1.4.dist-info/top_level.txt
wordpy-1.1.4.dist-info/RECORD
