Metadata-Version: 2.1
Name: wordpy
Version: 1.1.4
Summary: A dictionary program for nix* terminals
Home-page: https://github.com/mentix02/wordpy
Author: manan
Author-email: manan.yadav02@gmail.com
License: MIT
Keywords: wordpy dictionary api termdict
Platform: UNKNOWN
Classifier: Operating System :: Unix
Classifier: Operating System :: POSIX :: Linux
Classifier: Natural Language :: English
Classifier: License :: OSI Approved :: MIT License
Classifier: Programming Language :: Python :: 3.6
Classifier: Programming Language :: Python :: 3.7
Classifier: Programming Language :: Python :: 3.8
Classifier: Topic :: Utilities
Requires-Dist: requests (==2.21.0)
Requires-Dist: thesaurus (==0.2.3)
Requires-Dist: termcolor (==1.1.0)
